numberConversion/__init__.py
numberConversion/operations.py
numberConversion-0.3.dist-info/LICENSE
numberConversion-0.3.dist-info/METADATA
numberConversion-0.3.dist-info/WHEEL
numberConversion-0.3.dist-info/top_level.txt
numberConversion-0.3.dist-info/RECORD
