Metadata-Version: 2.1
Name: numberConversion
Version: 0.3
Summary: A simple package to convert decimal to binary and binary to decimal
Home-page: https://github.com/shresthaprayush2/numberconversion.git
Author: Prayush Shrestha
Author-email: prayushshrestha89@gmail.com
License: UNKNOWN
Platform: UNKNOWN
Classifier: Programming Language :: Python :: 3
Classifier: License :: OSI Approved :: MIT License
Classifier: Operating System :: OS Independent
Requires-Python: >=3.6
